README.txt
setup.py
toalaska/__init__.py
toalaska/clip.py
toalaska/mail_sender.py
toalaska/simple_mail_sender.py
toalaska/vars.py
toalaska.egg-info/PKG-INFO
toalaska.egg-info/SOURCES.txt
toalaska.egg-info/dependency_links.txt
toalaska.egg-info/top_level.txt
toalaska.egg-info/zip-safe